{
  "version": "134",
  "channel": "stable",
  "languages": [
    "en",
    "zh"
  ],
  "areas": [
    "css",
    "deprecations",
    "graphics-webgpu",
    "html-dom",
    "multimedia",
    "origin-trials",
    "other",
    "performance",
    "pwa-service-worker",
    "storage",
    "webapi"
  ],
  "total_areas": 11,
  "completed_areas": 3,
  "per_area": {
    "css": {
      "en": "error",
      "zh": "pending",
      "error": "Sampling timed out after 3 retries"
    },
    "deprecations": {
      "en": "error",
      "zh": "pending",
      "error": "Sampling timed out after 3 retries"
    },
    "graphics-webgpu": {
      "en": "error",
      "zh": "pending",
      "error": "Sampling timed out after 3 retries"
    }
  },
  "started_at": "2025-10-27T16:16:29.302116",
  "updated_at": "2025-10-27T16:19:39.609269"
}